audittools/__init__.py
audittools/audit_source.py
audittools/audits_rhsa.py
audittools/audits_usn.py
audittools/cve_class.py
audittools/redhat_cve.py
audittools/ubuntu_cve.py
audittools/verifyAudits.py
jelly_api_2/__init__.py
jelly_api_2/auditinfo.py
jelly_api_2/auditinfo_buckets.py
jelly_api_2/auditlist.py
jelly_api_2/auditresults.py
jelly_api_2/auditresults_range.py
jelly_api_2/auditresults_timestamp.py
jelly_api_2/collated.py
jelly_api_2/collected_root.py
jelly_api_2/collected_subtypes.py
jelly_api_2/collected_subtypes_filtered.py
jelly_api_2/collected_types.py
jelly_api_2/collected_values.py
jelly_api_2/custdashboard_create.py
jelly_api_2/custdashboard_dashboard.py
jelly_api_2/custdashboard_list.py
jelly_api_2/custdashboard_modify.py
jelly_api_2/cve_canonical.py
jelly_api_2/cve_canonical_check.py
jelly_api_2/dashboard.py
jelly_api_2/extendpopulationjson.py
jelly_api_2/factorlist.py
jelly_api_2/genericlargecompare.py
jelly_api_2/hostcollections.py
jelly_api_2/hostsearch.py
jelly_api_2/ipreport.py
jelly_api_2/ipsearch.py
jelly_api_2/puthostjson.py
jelly_api_2/root.py
jelly_api_2/sapi_addtoken.py
jelly_api_2/sapi_adduser.py
jelly_api_2/sapi_listusers.py
jelly_api_2/soc_vipporttohost.py
jelly_display_2/__init__.py
jelly_display_2/display_auditinfo.py
jelly_display_2/display_auditresults.py
jelly_display_2/display_auditslist.py
jelly_display_2/display_collatedresults.py
jelly_display_2/display_collected_subtype_filtered.py
jelly_display_2/display_collected_subtypes_filtered_search.py
jelly_display_2/display_collected_values.py
jelly_display_2/display_collected_values_search.py
jelly_display_2/display_custdashboard_create.py
jelly_display_2/display_custdashboard_create_results.py
jelly_display_2/display_custdashboard_modify.py
jelly_display_2/display_custdashboardlist.py
jelly_display_2/display_cve_canonical_check_results.py
jelly_display_2/display_cve_canonical_search.py
jelly_display_2/display_dashboard.py
jelly_display_2/display_hostcollections.py
manowar_server-2.6.2.dev3.dist-info/LICENSE
manowar_server-2.6.2.dev3.dist-info/METADATA
manowar_server-2.6.2.dev3.dist-info/WHEEL
manowar_server-2.6.2.dev3.dist-info/top_level.txt
manowar_server-2.6.2.dev3.dist-info/RECORD
