Metadata-Version: 2.1
Name: manowar-server
Version: 2.6.2.dev3
Summary: Server and Data Collection Components
Home-page: https://github.com/chalbersma/manowar
Author: Chris Halbersma
Author-email: chris+manowar@halbersma.us
License: BSD-2-Clause
Platform: UNKNOWN
Classifier: Development Status :: 2 - Pre-Alpha
Classifier: Programming Language :: Python :: 3.7
Classifier: License :: OSI Approved :: BSD License
Classifier: Operating System :: OS Independent
Classifier: Topic :: Security
Requires-Dist: PyYAML
Requires-Dist: flask
Requires-Dist: flask-cors
Requires-Dist: pymysql
Requires-Dist: manowar-agent
Requires-Dist: jsonschema
Requires-Dist: packaging
Requires-Dist: cvss
Requires-Dist: cpe
Requires-Dist: feedparser
Requires-Dist: pyjq
Requires-Dist: yoyo-database-migrations
Requires-Dist: pylxd
Requires-Dist: colorama
